.github/chart1.png
.github/chart10.png
.github/chart5.png
quotesaggregator/__init__.py
quotesaggregator/__main__.py
quotesaggregator/aggregator.py
quotesaggregator/settings.py
quotesaggregator/tests/__init__.py
quotesaggregator/tests/test_aggregator.py
quotesaggregator/utils.py
quotesaggregator-0.1.1.dist-info/entry_points.txt
quotesaggregator-0.1.1.dist-info/WHEEL
quotesaggregator-0.1.1.dist-info/METADATA
quotesaggregator-0.1.1.dist-info/RECORD
