Metadata-Version: 2.1
Name: quotesaggregator
Version: 0.1.1
Summary: QuotesAggregator is a quote aggregator program that stores the instant values of various currencies to create and save 1, 5 and 10 minute candles in a database through the Poloniex API.
Home-page: https://github.com/mrlucasrib/QuotesAggregator
License: MIT
Author: Lucas
Author-email: lmr2199@gmail.com
Requires-Python: >=3.8,<4.0
Classifier: License :: OSI Approved :: MIT License
Classifier: Programming Language :: Python :: 3
Classifier: Programming Language :: Python :: 3.8
Classifier: Programming Language :: Python :: 3.9
Requires-Dist: aiologger (>=0.6.1,<0.7.0)
Requires-Dist: aiomysql (>=0.0.21,<0.0.22)
Requires-Dist: asyncio (>=3.4.3,<4.0.0)
Requires-Dist: cryptography (>=3.4.7,<4.0.0)
Requires-Dist: prodict (>=0.8.16,<0.9.0)
Requires-Dist: pytz (>=2021.1,<2022.0)
Requires-Dist: websockets (>=9.0.1,<10.0.0)
Project-URL: Repository, https://github.com/mrlucasrib/QuotesAggregator
